geohashrs-0.1.4.dist-info/METADATA
geohashrs-0.1.4.dist-info/WHEEL
geohashrs.cpython-37m-x86_64-linux-gnu.so
geohashrs-0.1.4.dist-info/RECORD
