Metadata-Version: 2.1
Name: geohashrs
Version: 0.1.4
Classifier: Programming Language :: Python
Home-Page: https://github.com/blackrez/geohashrs
Author: nabil@eml.cc
Author-Email: nabil@eml.cc
Maintainer: Nabil Servais
Maintainer-Email: nabil@eml.cc
License: Apache-2.0
Requires-Python: >=3.5
